{
  "url": "https://kream.co.kr/products/24137",
  "name": "나이키 P-6000 메탈릭 실버",
  "brand": "Nike",
  "model_number": null,
  "release_price": "120166800",
  "current_price": "87000",
  "last_trade_price": "108000100009",
  "color": "metallic silver/sail/black",
  "description": "나이키 P-6000 메탈릭 실버",
  "delivery_info": "배송 정보",
  "image_url": "https://kream-phinf.pstatic.net/MjAyNDA2MjJfNDAg/MDAxNzE5MDMwNTAwMzQ3.XTwqEywpVW40rxeuHYJyRkWcfPpsjlcj4Chgc0vv9G4g.5qz49usEOZGuvLgSCOydMGx4NhNzqmM4H-B-ogKcBE4g.PNG/a_330e3ab56f174cd0a4f28eb06994ad2d.png?type=l",
  "review_count": 2480
}